{"firstName": "Svi", "lastName": "Mykhailiuk", "temporaryDisplayName": "Mykhailiuk, Svi", "personId": "1629004", "teamId": "1610612765", "jersey": "19", "isActive": true, "pos": "G", "heightFeet": "6", "heightInches": "8", "heightMeters": "2.03", "weightPounds": "205", "weightKilograms": "93.0", "dateOfBirthUTC": "1997-06-10", "teamSitesOnly": {"playerCode": "sviatoslav_mykhailiuk", "posFull": "Guard", "displayAffiliation": "Kansas/Ukraine", "freeAgentCode": ""}, "teams": [{"teamId": "1610612747", "seasonStart": "2018", "seasonEnd": "2018"}, {"teamId": "1610612765", "seasonStart": "2018", "seasonEnd": "2019"}], "draft": {"teamId": "1610612747", "pickNum": "47", "roundNum": "2", "seasonYear": "2018"}, "nbaDebutYear": "2018", "yearsPro": "1", "collegeName": "Kansas", "lastAffiliation": "University of Kansas/Ukraine", "country": "Ukraine"}