{"firstName": "Hamidou", "lastName": "Diallo", "temporaryDisplayName": "Diallo, Hamidou", "personId": "1628977", "teamId": "1610612760", "jersey": "6", "isActive": true, "pos": "G", "heightFeet": "6", "heightInches": "5", "heightMeters": "1.96", "weightPounds": "202", "weightKilograms": "91.6", "dateOfBirthUTC": "1998-07-31", "teamSitesOnly": {"playerCode": "hamidou_diallo", "posFull": "Guard", "displayAffiliation": "Kentucky/USA", "freeAgentCode": ""}, "teams": [{"teamId": "1610612760", "seasonStart": "2018", "seasonEnd": "2019"}], "draft": {"teamId": "1610612751", "pickNum": "45", "roundNum": "2", "seasonYear": "2018"}, "nbaDebutYear": "2018", "yearsPro": "1", "collegeName": "Kentucky", "lastAffiliation": "University of Kentucky/USA", "country": "USA"}