{"firstName": "Patrick", "lastName": "Beverley", "temporaryDisplayName": "Beverley, Patrick", "personId": "201976", "teamId": "1610612746", "jersey": "21", "isActive": true, "pos": "G", "heightFeet": "6", "heightInches": "1", "heightMeters": "1.85", "weightPounds": "185", "weightKilograms": "83.9", "dateOfBirthUTC": "1988-07-12", "teamSitesOnly": {"playerCode": "patrick_beverley", "posFull": "Guard", "displayAffiliation": "Arkansas/USA", "freeAgentCode": ""}, "teams": [{"teamId": "1610612745", "seasonStart": "2012", "seasonEnd": "2016"}, {"teamId": "1610612746", "seasonStart": "2017", "seasonEnd": "2019"}], "draft": {"teamId": "1610612747", "pickNum": "42", "roundNum": "2", "seasonYear": "2009"}, "nbaDebutYear": "2012", "yearsPro": "7", "collegeName": "Arkansas", "lastAffiliation": "Arkansas/USA", "country": "USA"}